LICENSE
MANIFEST.in
README.md
setup.py
extensisq/__init__.py
extensisq/bogacki.py
extensisq/calvo.py
extensisq/cash.py
extensisq/common.py
extensisq/fine.py
extensisq/merson.py
extensisq/mikkawy.py
extensisq/murua.py
extensisq/prince.py
extensisq/sensitivity.py
extensisq/shampine.py
extensisq/sommeijer.py
extensisq/tsitouras.py
extensisq.egg-info/PKG-INFO
extensisq.egg-info/SOURCES.txt
extensisq.egg-info/dependency_links.txt
extensisq.egg-info/requires.txt
extensisq.egg-info/top_level.txt
tests/test_ivp.py
tests/test_rk.py
tests/test_rkn.py
tests/test_sens.py