Metadata-Version: 2.1
Name: extensisq
Version: 0.5.0
Summary: Extend scipy.integrate with various methods for solve_ivp
Home-page: https://github.com/WRKampi/extensisq
Author: W.R. Kampinga
Author-email: wrkampi@tuta.io
Keywords: ode,ode-solver,ivp,ivp-methods,scipy,scipy-integrate,runge-kutta,runge-kutta-nystrom,differential-equations,cash-karp,prince,bogacki-shampine,adams,shampine-gordon,adams-bashforth-moulton,ode113,predictor-corrector,solver,sensitivity,sensitivity-analysis
Classifier: Development Status :: 3 - Alpha
Classifier: Programming Language :: Python :: 3
Classifier: License :: OSI Approved :: MIT License
Classifier: Operating System :: OS Independent
Classifier: Intended Audience :: Science/Research
Classifier: Intended Audience :: Developers
Classifier: Topic :: Scientific/Engineering
Classifier: Topic :: Scientific/Engineering :: Mathematics
Classifier: Topic :: Scientific/Engineering :: Physics
Requires-Python: >=3.8
License-File: LICENSE
Requires-Dist: numpy>=1.22.0
Requires-Dist: scipy>=1.8.0
